django_object_authority
django_object_authority/management/commands
