Metadata-Version: 1.1
Name: django-object-authority
Version: 0.0.4
Summary: Package to authorize actions (CRUD) to users over concrete items.
Home-page: http://github.com/bcanyelles/django-object-authority/
Author: Tomeu Canyelles
Author-email: bcanyelles@apsl.net
License: BSD
Platform: UNKNOWN
Classifier: Intended Audience :: Developers
Classifier: License :: OSI Approved :: BSD License
Classifier: Operating System :: OS Independent
Classifier: Programming Language :: Python
Classifier: Programming Language :: Python :: 3
